README.rst
setup.py
testfunc.py
testfunc.egg-info/PKG-INFO
testfunc.egg-info/SOURCES.txt
testfunc.egg-info/dependency_links.txt
testfunc.egg-info/requires.txt
testfunc.egg-info/top_level.txt