Metadata-Version: 1.1
Name: testfunc
Version: 0.1
Summary: A sample tool for testing functions
Home-page: https://github.com/yanxurui/testfunc
Author: Xurui Yan
Author-email: yxr1993@gmail.com
License: MIT
Keywords: test
Platform: UNKNOWN
Classifier: Development Status :: 5 - Production/Stable
Classifier: Topic :: Software Development :: Testing
Classifier: Intended Audience :: Developers
Classifier: License :: OSI Approved :: MIT License
Classifier: Programming Language :: Python :: 2
Classifier: Programming Language :: Python :: 2.7
